ai_credentials-0.1.2.dist-info/METADATA
ai_credentials-0.1.2.dist-info/WHEEL
ai_credentials/__init__.py
ai_credentials/ai_credentials.cpython-313-darwin.so
ai_credentials-0.1.2.dist-info/RECORD
